README.md
setup.py
bin/hither2-compute-resource
hither2/__init__.py
hither2/_consolecapture.py
hither2/_etconf.py
hither2/_filelock.py
hither2/_generate_source_code_for_function.py
hither2/_load_config.py
hither2/_preventkeyboardinterrupt.py
hither2/_run_serialized_job_in_container.py
hither2/_shellscript.py
hither2/_temporarydirectory.py
hither2/_util.py
hither2/computeresource.py
hither2/core.py
hither2/database.py
hither2/file.py
hither2/jobcache.py
hither2/paralleljobhandler.py
hither2/remotejobhandler.py
hither2/slurmjobhandler.py
hither2.egg-info/PKG-INFO
hither2.egg-info/SOURCES.txt
hither2.egg-info/dependency_links.txt
hither2.egg-info/requires.txt
hither2.egg-info/top_level.txt
tests/__init__.py
tests/misc_functions.py
tests/test_1.py
tests/test_shellscript.py