Metadata-Version: 1.1
Name: hither2
Version: 0.1.2
Summary: Run batches of Python functions in containers and on remote servers
Home-page: UNKNOWN
Author: Jeremy Magland
Author-email: jmagland@flatironinstitute.org
License: UNKNOWN
Platform: UNKNOWN
Classifier: Programming Language :: Python :: 3
Classifier: License :: OSI Approved :: Apache Software License
Classifier: Operating System :: OS Independent
